ram_1.v
module single_port_ram(
  input[7:0] data,
  input [5:0] addr,
  input we,
  input clk,
  output [7:0] q
);
  reg [7:0] ram [63:0];// 64 bit ram
  reg [5:0] addr_reg; // address register
   
  always@(posedge clk)
    begin
      if(we)
        ram[addr]<= data;
      else
        addr_reg<= addr;
      
    end
  assign q= ram[addr_reg];
endmodule

ram_tb.v
`timescale 1ns/1ns
 `include "ram_1.v"
 module single_port_ram_tb;
  reg[7:0]data;
  reg [5:0] addr;
  reg we;
  reg clk;
  wire [7:0] q;
  
  single_port_ram spr1(
    .data(data),
    .addr(addr),
    .we(we),
    .clk(clk),
    .q(q));
  initial 
    begin
      $dumpfile("ram_tb.vcd");
      $dumpvars(0,single_port_ram_tb);
      $monitor($time,"data=%h, addr=%d, we=%b",data,addr,we);
      
      clk=1'b1;
      forever #5 clk=~clk;
    end
  
  initial
    begin 
      data =8'b01;
      addr=5'd0;
      we=1'b1;
      #10;
      
      data =8'h02;
      addr=5'd1;
      #10;
      
      data =8'h03;
      addr =5'd2;
      #10;
      addr=5'd0;
      we=1'b0;
      #10;
      
      addr=5'd1;
      #10;
      
      addr =5'd2;
      #10
      
      data=8'h04;
      addr=5'd1;
      we=1'b1;
      #10;
      
      addr=5'd1;
      we=1'b0;
      #10;
      
       $finish;
      #10;
    end
endmodule

ram_tb.vcd
$date
	Mon Jul 29 19:47:47 2024
$end
$version
	Icarus Verilog
$end
$timescale
	1ns
$end
$scope module single_port_ram_tb $end
$var wire 8 ! q [7:0] $end
$var reg 6 " addr [5:0] $end
$var reg 1 # clk $end
$var reg 8 $ data [7:0] $end
$var reg 1 % we $end
$scope module spr1 $end
$var wire 6 & addr [5:0] $end
$var wire 1 # clk $end
$var wire 8 ' data [7:0] $end
$var wire 8 ( q [7:0] $end
$var wire 1 % we $end
$var reg 6 ) addr_reg [5:0] $end
$upscope $end
$upscope $end
$enddefinitions $end
$comment Show the parameter values. $end
$dumpall
$end
#0
$dumpvars
bx )
bx (
b1 '
b0 &
1%
b1 $
1#
b0 "
bx !
$end
#5
0#
#10
1#
b1 "
b1 &
b10 $
b10 '
#15
0#
#20
1#
b10 "
b10 &
b11 $
b11 '
#25
0#
#30
b1 !
b1 (
b0 )
1#
0%
b0 "
b0 &
#35
0#
#40
b10 !
b10 (
b1 )
1#
b1 "
b1 &
#45
0#
#50
b11 !
b11 (
b10 )
1#
b10 "
b10 &
#55
0#
#60
1#
1%
b1 "
b1 &
b100 $
b100 '
#65
0#
#70
b100 !
b100 (
b1 )
1#
0%
